as4012_sstr/__init__.py
as4012_sstr/as4012_sstr_version.py
as4012_sstr/reader.py
as4012_sstr-1.0.0.dist-info/METADATA
as4012_sstr-1.0.0.dist-info/WHEEL
as4012_sstr-1.0.0.dist-info/licenses/LICENSE
as4012_sstr-1.0.0.dist-info/RECORD
